{
  "hash": "da128af3",
  "configHash": "13381830",
  "lockfileHash": "e15442d0",
  "browserHash": "07eab9fb",
  "optimized": {
    "react": {
      "src": "../../node_modules/react/index.js",
      "file": "react.js",
      "fileHash": "c72b32f6",
      "needsInterop": true
    },
    "react-dom/client": {
      "src": "../../node_modules/react-dom/client.js",
      "file": "react-dom_client.js",
      "fileHash": "d38e167f",
      "needsInterop": true
    },
    "react-router-dom": {
      "src": "../../node_modules/react-router-dom/dist/index.mjs",
      "file": "react-router-dom.js",
      "fileHash": "055a0748",
      "needsInterop": false
    },
    "lucide-react": {
      "src": "../../node_modules/lucide-react/dist/esm/lucide-react.js",
      "file": "lucide-react.js",
      "fileHash": "646a5025",
      "needsInterop": false
    },
    "react-icons/fa": {
      "src": "../../node_modules/react-icons/fa/index.mjs",
      "file": "react-icons_fa.js",
      "fileHash": "8712a2ca",
      "needsInterop": false
    },
    "framer-motion": {
      "src": "../../node_modules/framer-motion/dist/es/index.mjs",
      "file": "framer-motion.js",
      "fileHash": "42575d7e",
      "needsInterop": false
    }
  },
  "chunks": {
    "chunk-MBB5IPWF": {
      "file": "chunk-MBB5IPWF.js"
    },
    "chunk-N2EVEQ7D": {
      "file": "chunk-N2EVEQ7D.js"
    }
  }
}